[
  {
    "key": "快播云",
    "id": 1,
    "name": "快播云",
    "api": "http://www.kuaibozy.com/api.php/provide/vod/from/kbm3u8/at/xml/",
    "download": "",
    "jiexiUrl": "https://jx.7kjx.com/?url=",
    "group": "默认",
    "isActive": true,
    "status": "可用",
    "reverseOrder": true
  },
  {
    "key": "天空云",
    "id": 4,
    "name": "天空云",
    "api": "https://api.tiankongapi.com/api.php/provide/vod/at/xml/from/tkm3u8/",
    "download": "",
    "jiexiUrl": "https://jx.7kjx.com/?url=",
    "group": "默认",
    "isActive": true,
    "status": "可用",
    "reverseOrder": false
  },
  {
    "key": "八戒云",
    "id": 5,
    "name": "八戒云",
    "api": "http://cj.bajiecaiji.com/inc/bjm3u8.php",
    "download": "",
    "jiexiUrl": "",
    "group": "默认",
    "isActive": true,
    "status": "可用",
    "reverseOrder": false
  },
  {
    "key": "88zyw",
    "id": 6,
    "name": "88 影视",
    "api": "http://www.88zyw.net/inc/api.php",
    "download": "",
    "jiexiUrl": "",
    "group": "默认",
    "isActive": true,
    "status": "可用",
    "reverseOrder": false
  },
  {
    "key": "rrzy",
    "id": 7,
    "name": "人人资源",
    "api": "https://www.rrzyw.cc/api.php/provide/vod/from/rrm3u8/at/xml/",
    "download": "",
    "jiexiUrl": "https://jx.7kjx.com/?url=",
    "group": "默认",
    "isActive": true,
    "status": "可用",
    "reverseOrder": false
  },
  {
    "id": 8,
    "key": "lyzy",
    "name": "老鸭资源",
    "api": "https://api.apilyzy.com/api.php/Seacms/vod/",
    "download": "",
    "jiexiUrl": "",
    "group": "常用组",
    "isActive": true,
    "reverseOrder": false,
    "status": "可用"
  },
  {
    "id": 9,
    "key": "bdzy2",
    "name": "百度资源2",
    "api": "https://cj.apibdzy.com/inc/api.php",
    "download": "",
    "jiexiUrl": "",
    "group": "常用组",
    "isActive": true,
    "reverseOrder": false,
    "status": "可用"
  },
  {
    "id": 10,
    "key": "hjzy",
    "name": "花椒资源",
    "api": "https://apihjzy.com/api.php/Seacms/vod/",
    "download": "",
    "jiexiUrl": "",
    "group": "常用组",
    "isActive": true,
    "reverseOrder": false,
    "status": "可用"
  },
  {
    "id": 11,
    "key": "zkzy",
    "name": "最快资源",
    "api": "http://cj.1886zy.co/inc/seacmsapi.php",
    "download": "",
    "jiexiUrl": "",
    "group": "常用组",
    "isActive": true,
    "reverseOrder": false,
    "status": "可用"
  },
  {
    "id": 12,
    "key": "6uzy",
    "name": "6U资源",
    "api": "http://zy.ataoju.com/inc/api.php",
    "download": "",
    "jiexiUrl": "",
    "group": "常用组",
    "isActive": true,
    "reverseOrder": false,
    "status": "可用"
  },
  {
    "id": 13,
    "key": "ldzyw",
    "name": "乐多资源网",
    "api": "http://api.leduozy.com/inc/api.php",
    "download": "",
    "jiexiUrl": "",
    "group": "常用组",
    "isActive": true,
    "reverseOrder": false,
    "status": "可用"
  },
  {
    "id": 14,
    "key": "605zy",
    "name": "605资源",
    "api": "http://www.605zy.co/inc/api.php",
    "download": "",
    "jiexiUrl": "",
    "group": "常用组",
    "isActive": true,
    "reverseOrder": false,
    "status": "可用"
  },
  {
    "id": 15,
    "key": "bttcj",
    "name": "BT天堂",
    "api": "http://bttcj.com/inc/sapi.php",
    "download": "",
    "jiexiUrl": "",
    "group": "常用组",
    "isActive": true,
    "reverseOrder": false,
    "status": "可用"
  },
  {
    "id": 17,
    "key": "39kan",
    "name": "39影视",
    "api": "https://www.39kan.com/api.php/provide/vod/at/xml",
    "download": "",
    "jiexiUrl": "",
    "group": "常用组",
    "isActive": true,
    "reverseOrder": false,
    "status": "可用"
  },
  {
    "id": 18,
    "key": "ct",
    "name": "苍天",
    "api": "http://cj.cangtiancj.com/api.php/Seacms/vod/",
    "download": "",
    "jiexiUrl": "",
    "group": "18禁",
    "isActive": true,
    "reverseOrder": false,
    "status": "可用"
  },
  {
    "id": 19,
    "key": "lb",
    "name": "乐播",
    "api": "https://lbapi9.com/api.php/provide/vod/at/xml/",
    "download": "",
    "jiexiUrl": "",
    "group": "18禁",
    "isActive": true,
    "reverseOrder": false,
    "status": "可用"
  },
  {
    "id": 20,
    "key": "76",
    "name": "76",
    "api": "http://m.7777688.com/inc/api.php",
    "download": "",
    "jiexiUrl": "",
    "group": "18禁",
    "isActive": true,
    "reverseOrder": false,
    "status": "可用"
  },
  {
    "id": 21,
    "key": "sy",
    "name": "shayu",
    "api": "https://shayuapi.com/api.php/Seacms/vod/",
    "download": "",
    "jiexiUrl": "",
    "group": "18禁",
    "isActive": true,
    "reverseOrder": false,
    "status": "可用"
  },
  {
    "id": 22,
    "key": "dd",
    "name": "大地",
    "api": "https://dadiapi.com/api.php",
    "download": "",
    "jiexiUrl": "",
    "group": "18禁",
    "isActive": true,
    "reverseOrder": false,
    "status": "可用"
  },
  {
    "id": 23,
    "key": "wmcj8",
    "name": "环亚资源",
    "api": "http://wmcj8.com/inc/sapi.php",
    "download": "",
    "jiexiUrl": "",
    "group": "18禁",
    "isActive": true,
    "reverseOrder": false,
    "status": "可用"
  },
  {
    "id": 24,
    "key": "jl",
    "name": "佳丽",
    "api": "https://jialiapi.com/api.php/provide/vod/at/xml/",
    "download": "",
    "jiexiUrl": "",
    "group": "18禁",
    "isActive": true,
    "reverseOrder": false,
    "status": "可用"
  },
  {
    "key": "TVB云播",
    "id": 27,
    "name": "TVB云播",
    "api": "https://www.hktvyb.com/api.php/provide/vod/at/xml/",
    "download": "",
    "jiexiUrl": "https://9kjx.com/?url=",
    "group": "默认",
    "isActive": true,
    "status": "可用",
    "reverseOrder": false
  },
  {
    "key": "天堂资源",
    "id": 28,
    "name": "天堂资源",
    "api": "http://vipmv.cc/api.php/provide/vod/at/xml/\n",
    "download": "",
    "jiexiUrl": "https://titan.mgtv.com.o8tv.com/jiexi/?url=",
    "group": "默认",
    "isActive": true,
    "status": "可用",
    "reverseOrder": false
  },
  {
    "key": "2A资源站",
    "id": 29,
    "name": "明日资源",
    "api": "https://zy.zcocc.com/api.php/provide/vod/at/xml/",
    "download": "",
    "jiexiUrl": "https://jx.xmflv.com/?url=",
    "group": "默认",
    "isActive": true,
    "status": "可用",
    "reverseOrder": false
  },
  {
    "key": "8090资源",
    "id": 30,
    "name": "8090资源",
    "api": "http://zy.yilans.net:8090/api.php/provide/vod/at/xml/",
    "download": "",
    "jiexiUrl": "https://9kjx.com/?url=",
    "group": "默认",
    "isActive": true,
    "status": "可用",
    "reverseOrder": false
  },
  {
    "key": "萌果资源",
    "id": 31,
    "name": "萌果资源",
    "api": "http://api.appearoo.top/api.php/provide/vod/at/xml/",
    "download": "",
    "jiexiUrl": "http://jx.maguays.cc/?url=\n",
    "group": "默认",
    "isActive": true,
    "status": "可用",
    "reverseOrder": false
  },
  {
    "key": "橘猫影视",
    "id": 33,
    "name": "橘猫影视",
    "api": "http://www.zitv.cc/api.php/provide/vod/at/xml/",
    "download": "",
    "jiexiUrl": "http://jx.hao-zsj.cn/vip/?url=",
    "group": "聚合",
    "isActive": true,
    "status": "可用",
    "reverseOrder": false
  },
  {
    "key": "乐活影视",
    "id": 34,
    "name": "乐活影视",
    "api": "https://lehootv.com/api.php/provide/vod/at/xml/",
    "download": "",
    "jiexiUrl": "http://jx.hao-zsj.cn/vip/?url=",
    "group": "优质",
    "isActive": true,
    "status": "可用",
    "reverseOrder": false
  },
  {
    "key": "八戒资源",
    "id": 37,
    "name": "八戒资源",
    "api": "http://cj.bajiecaiji.com/inc/api.php",
    "download": "",
    "group": "切片",
    "isActive": true,
    "status": "可用",
    "reverseOrder": false
  },
  {
    "key": "88资源",
    "id": 40,
    "name": "88资源",
    "api": "http://www.88zyw.net/inc/api.php",
    "download": "",
    "group": "切片",
    "isActive": true,
    "status": "可用",
    "reverseOrder": false
  },
  {
    "key": "快播资源",
    "id": 128,
    "name": "快播资源",
    "api": "http://www.kuaibozy.com/api.php/provide/vod/at/xml/",
    "download": "",
    "group": "切片",
    "isActive": true,
    "status": "可用",
    "reverseOrder": false
  },
  {
    "key": "lyuzy",
    "id": 129,
    "name": "乐鱼资源",
    "api": "https://www.leyuzyapi.com/inc/seacmsapi.php",
    "download": "",
    "jiexiUrl": "https://player.leyuzy.net/?url=",
    "group": "需解析",
    "isActive": true,
    "reverseOrder": false,
    "status": "可用"
  },
  {
    "key": "lczy",
    "id": 130,
    "name": "奶茶资源",
    "api": "https://caiji.naichaapi.com/inc/seacmsapi.php",
    "download": "",
    "jiexiUrl": "https://jiexi.naichaapi.com/?url=",
    "group": "需解析",
    "isActive": true,
    "reverseOrder": false,
    "status": "可用"
  },
  {
    "key": "xszyw",
    "id": 131,
    "name": "523资源网",
    "api": "https://caiji.523zyw.com/inc/seacmsapi.php",
    "download": "",
    "jiexiUrl": "",
    "group": "18禁",
    "isActive": true,
    "reverseOrder": false,
    "status": "可用"
  },
  {
    "key": "美少女资源站",
    "id": 132,
    "name": "美少女资源站",
    "api": "https://www.msnii.com/api/xml.php",
    "download": "",
    "jiexiUrl": "",
    "group": "18禁",
    "isActive": true,
    "reverseOrder": false,
    "status": "可用"
  },
  {
    "key": "淫水机资源站",
    "id": 133,
    "name": "淫水机资源站",
    "api": "https://www.xrbsp.com/api/xml.php",
    "download": "",
    "jiexiUrl": "",
    "group": "18禁",
    "isActive": true,
    "reverseOrder": false,
    "status": "可用"
  },
  {
    "key": "香奶儿资源站",
    "id": 134,
    "name": "香奶儿资源站",
    "api": "https://www.gdlsp.com/api/xml.php",
    "download": "",
    "jiexiUrl": "",
    "group": "18禁",
    "isActive": true,
    "reverseOrder": false,
    "status": "可用"
  },
  {
    "key": "白嫖资源站",
    "id": 135,
    "name": "白嫖资源站",
    "api": "https://www.kxgav.com/api/xml.php",
    "download": "",
    "jiexiUrl": "",
    "group": "18禁",
    "isActive": true,
    "reverseOrder": false,
    "status": "可用"
  },
  {
    "key": "小湿妹资源站",
    "id": 136,
    "name": "小湿妹资源站",
    "api": "https://www.afasu.com/api/xml.php",
    "download": "",
    "jiexiUrl": "",
    "group": "18禁",
    "isActive": true,
    "reverseOrder": false,
    "status": "可用"
  },
  {
    "key": "黄AV资源站",
    "id": 137,
    "name": "黄AV资源站",
    "api": "https://www.pgxdy.com/api/xml.php",
    "download": "",
    "jiexiUrl": "",
    "group": "18禁",
    "isActive": true,
    "reverseOrder": false,
    "status": "可用"
  },
  {
    "key": "芒果资源",
    "id": 138,
    "name": "芒果资源",
    "api": "https://mgzyz1.com/api.php/provide/vod/at/xml/",
    "download": "",
    "jiexiUrl": "https://mgm3u8-player.com/player/DPm3u8.php?url=",
    "group": "需解析",
    "isActive": true,
    "reverseOrder": false,
    "status": "可用"
  },
  {
    "key": "探探资源",
    "id": 139,
    "name": "探探资源",
    "api": "https://cdn.apittzy.com/api.php/Seacms/vod/",
    "download": "",
    "jiexiUrl": "https://jiexi.ttbfp1.com/m3u8/?url=",
    "group": "需解析",
    "isActive": true,
    "reverseOrder": false,
    "status": "可用"
  },
  {
    "key": "爱播视频",
    "id": 140,
    "name": "爱播视频",
    "api": "https://api.aibozyapi.com/vod/cms/sea/at/xml",
    "download": "",
    "jiexiUrl": "https://player.aibozyplayer.com/m3u8/?url=",
    "group": "需解析",
    "isActive": true,
    "reverseOrder": false,
    "status": "可用"
  }
]
